lzhgetlogger/__init__.py
lzhgetlogger/logger.py
lzhgetlogger-1.0.dist-info/METADATA
lzhgetlogger-1.0.dist-info/WHEEL
lzhgetlogger-1.0.dist-info/top_level.txt
lzhgetlogger-1.0.dist-info/RECORD
