Metadata-Version: 2.4
Name: lzhgetlogger
Version: 1.0
Summary: 简化 logging 配置，统一格式
Author-email: lzh <zhhtdm@hotmail.com>
License: MIT
Project-URL: Homepage, https://github.com/zhhtdm/get-logger
Project-URL: Repository, https://github.com/zhhtdm/get-logger
Requires-Python: >=3.7
